minislurm/__init__.py
minislurm/minislurm_client.py
minislurm/minislurm_server.py
minislurm-21.11.dist-info/LICENSE
minislurm-21.11.dist-info/METADATA
minislurm-21.11.dist-info/WHEEL
minislurm-21.11.dist-info/entry_points.txt
minislurm-21.11.dist-info/top_level.txt
minislurm-21.11.dist-info/RECORD
