Metadata-Version: 2.1
Name: minislurm
Version: 21.11
Summary: Single machine resource manager
Home-page: https://gitlab.com/matsievskiysv/minislurm
Author: S.V. Matsievskiy
Author-email: matsievskiysv@gmail.com
Maintainer: S.V. Matsievskiy
Maintainer-email: matsievskiysv@gmail.com
License: AGPLv3+
Keywords: job queue
Platform: UNKNOWN
Classifier: Development Status :: 4 - Beta
Classifier: Environment :: Console
Classifier: Intended Audience :: Science/Research
Classifier: License :: OSI Approved :: GNU Affero General Public License v3 or later (AGPLv3+)
Classifier: Operating System :: Unix
Classifier: Programming Language :: Python :: 3 :: Only
Classifier: Topic :: Scientific/Engineering
License-File: LICENSE
Requires-Dist: docopt
